couchbasepypdu.pypy310-pp73-x86_64-linux-gnu.so
couchbasepypdu-0.1.13.dist-info/NOTICE
couchbasepypdu-0.1.13.dist-info/top_level.txt
couchbasepypdu-0.1.13.dist-info/LICENSE
couchbasepypdu-0.1.13.dist-info/RECORD
couchbasepypdu-0.1.13.dist-info/METADATA
couchbasepypdu-0.1.13.dist-info/WHEEL
