Metadata-Version: 2.1
Name: couchbasepypdu
Version: 0.1.13
Summary: Python bindings for C++ library for reading Prometheus on-disk data
Author: jameseh96
Author-email: 
Project-URL: Source, https://github.com/jameseh96/pdu
License-File: LICENSE
License-File: NOTICE
Provides-Extra: numpy
Requires-Dist: numpy; extra == "numpy"
